<?xml version="1.0" encoding="UTF-8"?>
<ss><gms gd="0" w="3" y="1970" t="R"><g eid="1970100301" gsis="8224" d="Sat" t="3:00" q="F" k="" h="CLE" hnn="browns" hs="15" v="PIT" vnn="steelers" vs="7" p="" rz="" ga="" gt="REG"/><g eid="1970100300" gsis="8224" d="Sat" t="3:00" q="F" k="" h="MIA" hnn="dolphins" hs="20" v="OAK" vnn="raiders" vs="13" p="" rz="" ga="" gt="REG"/><g eid="1970100401" gsis="8224" d="Sun" t="3:00" q="F" k="" h="NO" hnn="saints" hs="14" v="NYG" vnn="giants" vs="10" p="" rz="" ga="" gt="REG"/><g eid="1970100400" gsis="8224" d="Sun" t="3:00" q="F" k="" h="GB" hnn="packers" hs="13" v="MIN" vnn="vikings" vs="10" p="" rz="" ga="" gt="REG"/><g eid="1970100409" gsis="8224" d="Sun" t="3:00" q="F" k="" h="STL" hnn="cardinals" hs="20" v="DAL" vnn="cowboys" vs="7" p="" rz="" ga="" gt="REG"/><g eid="1970100403" gsis="8224" d="Sun" t="3:00" q="F" k="" h="BOS" hnn="patriots" hs="6" v="BAL" vnn="colts" vs="14" p="" rz="" ga="" gt="REG"/><g eid="1970100404" gsis="8224" d="Sun" t="3:00" q="F" k="" h="CIN" hnn="bengals" hs="13" v="HOU" vnn="oilers" vs="20" p="" rz="" ga="" gt="REG"/><g eid="1970100402" gsis="8224" d="Sun" t="3:00" q="F" k="" h="ATL" hnn="falcons" hs="21" v="SF" vnn="49ers" vs="20" p="" rz="" ga="" gt="REG"/><g eid="1970100408" gsis="8224" d="Sun" t="3:00" q="F" k="" h="LA" hnn="rams" hs="37" v="SD" vnn="chargers" vs="10" p="" rz="" ga="" gt="REG"/><g eid="1970100407" gsis="8224" d="Sun" t="3:00" q="F" k="" h="PHI" hnn="eagles" hs="21" v="WAS" vnn="redskins" vs="33" p="" rz="" ga="" gt="REG"/><g eid="1970100406" gsis="8224" d="Sun" t="3:00" q="F" k="" h="BUF" hnn="bills" hs="34" v="NYJ" vnn="jets" vs="31" p="" rz="" ga="" gt="REG"/><g eid="1970100405" gsis="8224" d="Sun" t="3:00" q="F" k="" h="DEN" hnn="broncos" hs="26" v="KC" vnn="chiefs" vs="13" p="" rz="" ga="" gt="REG"/><g eid="1970100500" gsis="8224" d="Mon" t="3:00" q="F" k="" h="DET" hnn="lions" hs="28" v="CHI" vnn="bears" vs="14" p="" rz="" ga="" gt="REG"/></gms></ss>