<?xml version="1.0" encoding="UTF-8"?>
<ss><gms gd="0" w="11" y="1971" t="R"><g eid="1971112500" gsis="8224" d="Thu" t="3:00" q="F" k="" h="DET" hnn="lions" hs="32" v="KC" vnn="chiefs" vs="21" p="" rz="" ga="" gt="REG"/><g eid="1971112501" gsis="8224" d="Thu" t="3:00" q="F" k="" h="DAL" hnn="cowboys" hs="28" v="LA" vnn="rams" vs="21" p="" rz="" ga="" gt="REG"/><g eid="1971112809" gsis="8224" d="Sun" t="3:00" q="F" k="" h="NYG" hnn="giants" hs="7" v="STL" vnn="cardinals" vs="24" p="" rz="" ga="" gt="REG"/><g eid="1971112808" gsis="8224" d="Sun" t="3:00" q="F" k="" h="GB" hnn="packers" hs="21" v="NO" vnn="saints" vs="29" p="" rz="" ga="" gt="REG"/><g eid="1971112807" gsis="8224" d="Sun" t="3:00" q="F" k="" h="MIN" hnn="vikings" hs="24" v="ATL" vnn="falcons" vs="7" p="" rz="" ga="" gt="REG"/><g eid="1971112806" gsis="8224" d="Sun" t="3:00" q="F" k="" h="PIT" hnn="steelers" hs="10" v="DEN" vnn="broncos" vs="22" p="" rz="" ga="" gt="REG"/><g eid="1971112805" gsis="8224" d="Sun" t="3:00" q="F" k="" h="HOU" hnn="oilers" hs="24" v="CLE" vnn="browns" vs="37" p="" rz="" ga="" gt="REG"/><g eid="1971112804" gsis="8224" d="Sun" t="3:00" q="F" k="" h="OAK" hnn="raiders" hs="14" v="BAL" vnn="colts" vs="37" p="" rz="" ga="" gt="REG"/><g eid="1971112800" gsis="8224" d="Sun" t="3:00" q="F" k="" h="BUF" hnn="bills" hs="27" v="NE" vnn="patriots" vs="20" p="" rz="" ga="" gt="REG"/><g eid="1971112801" gsis="8224" d="Sun" t="3:00" q="F" k="" h="CIN" hnn="bengals" hs="31" v="SD" vnn="chargers" vs="0" p="" rz="" ga="" gt="REG"/><g eid="1971112803" gsis="8224" d="Sun" t="3:00" q="F" k="" h="PHI" hnn="eagles" hs="13" v="WAS" vnn="redskins" vs="20" p="" rz="" ga="" gt="REG"/><g eid="1971112802" gsis="8224" d="Sun" t="3:00" q="F" k="" h="NYJ" hnn="jets" hs="21" v="SF" vnn="49ers" vs="24" p="" rz="" ga="" gt="REG"/><g eid="1971112900" gsis="8224" d="Mon" t="3:00" q="F" k="" h="MIA" hnn="dolphins" hs="34" v="CHI" vnn="bears" vs="3" p="" rz="" ga="" gt="REG"/></gms></ss>