<?xml version="1.0" encoding="UTF-8"?>
<ss><gms gd="0" w="10" y="1973" t="R"><g eid="1973111811" gsis="8224" d="Sun" t="3:00" q="F" k="" h="OAK" hnn="raiders" hs="3" v="CLE" vnn="browns" vs="7" p="" rz="" ga="" gt="REG"/><g eid="1973111810" gsis="8224" d="Sun" t="3:00" q="F" k="" h="NYG" hnn="giants" hs="24" v="STL" vnn="cardinals" vs="13" p="" rz="" ga="" gt="REG"/><g eid="1973111809" gsis="8224" d="Sun" t="3:00" q="F" k="" h="LA" hnn="rams" hs="31" v="SF" vnn="49ers" vs="13" p="" rz="" ga="" gt="REG"/><g eid="1973111808" gsis="8224" d="Sun" t="3:00" q="F" k="" h="DAL" hnn="cowboys" hs="31" v="PHI" vnn="eagles" vs="10" p="" rz="" ga="" gt="REG"/><g eid="1973111807" gsis="8224" d="Sun" t="3:00" q="F" k="" h="SD" hnn="chargers" hs="17" v="NO" vnn="saints" vs="14" p="" rz="" ga="" gt="REG"/><g eid="1973111806" gsis="8224" d="Sun" t="3:00" q="F" k="" h="NE" hnn="patriots" hs="33" v="GB" vnn="packers" vs="24" p="" rz="" ga="" gt="REG"/><g eid="1973111805" gsis="8224" d="Sun" t="3:00" q="F" k="" h="CIN" hnn="bengals" hs="20" v="NYJ" vnn="jets" vs="14" p="" rz="" ga="" gt="REG"/><g eid="1973111804" gsis="8224" d="Sun" t="3:00" q="F" k="" h="CHI" hnn="bears" hs="7" v="DET" vnn="lions" vs="30" p="" rz="" ga="" gt="REG"/><g eid="1973111803" gsis="8224" d="Sun" t="3:00" q="F" k="" h="BUF" hnn="bills" hs="0" v="MIA" vnn="dolphins" vs="17" p="" rz="" ga="" gt="REG"/><g eid="1973111802" gsis="8224" d="Sun" t="3:00" q="F" k="" h="WAS" hnn="redskins" hs="22" v="BAL" vnn="colts" vs="14" p="" rz="" ga="" gt="REG"/><g eid="1973111801" gsis="8224" d="Sun" t="3:00" q="F" k="" h="KC" hnn="chiefs" hs="38" v="HOU" vnn="oilers" vs="14" p="" rz="" ga="" gt="REG"/><g eid="1973111800" gsis="8224" d="Sun" t="3:00" q="F" k="" h="PIT" hnn="steelers" hs="13" v="DEN" vnn="broncos" vs="23" p="" rz="" ga="" gt="REG"/><g eid="1973111900" gsis="8224" d="Mon" t="3:00" q="F" k="" h="ATL" hnn="falcons" hs="20" v="MIN" vnn="vikings" vs="14" p="" rz="" ga="" gt="REG"/></gms></ss>