<?xml version="1.0" encoding="UTF-8"?>
<ss><gms gd="0" w="5" y="1983" t="R"><g eid="1983100204" gsis="8224" d="Sun" t="3:00" q="F" k="" h="NE" hnn="patriots" hs="13" v="SF" vnn="49ers" vs="33" p="" rz="" ga="" gt="REG"/><g eid="1983100203" gsis="8224" d="Sun" t="3:00" q="F" k="" h="WAS" hnn="redskins" hs="37" v="RAI" vnn="raiders" vs="35" p="" rz="" ga="" gt="REG"/><g eid="1983100202" gsis="8224" d="Sun" t="3:00" q="F" k="" h="PIT" hnn="steelers" hs="17" v="HOU" vnn="oilers" vs="10" p="" rz="" ga="" gt="REG"/><g eid="1983100201" gsis="8224" d="Sun" t="3:00" q="F" k="" h="CIN" hnn="bengals" hs="31" v="BAL" vnn="colts" vs="34" p="" rz="" ga="" gt="REG"/><g eid="1983100200" gsis="8224" d="Sun" t="3:00" q="F" k="" h="CHI" hnn="bears" hs="31" v="DEN" vnn="broncos" vs="14" p="" rz="" ga="" gt="REG"/><g eid="1983100212" gsis="8224" d="Sun" t="3:00" q="F" k="" h="ATL" hnn="falcons" hs="24" v="PHI" vnn="eagles" vs="28" p="" rz="" ga="" gt="REG"/><g eid="1983100205" gsis="8224" d="Sun" t="3:00" q="F" k="" h="NO" hnn="saints" hs="17" v="MIA" vnn="dolphins" vs="7" p="" rz="" ga="" gt="REG"/><g eid="1983100211" gsis="8224" d="Sun" t="3:00" q="F" k="" h="RAM" hnn="rams" hs="21" v="DET" vnn="lions" vs="10" p="" rz="" ga="" gt="REG"/><g eid="1983100210" gsis="8224" d="Sun" t="3:00" q="F" k="" h="MIN" hnn="vikings" hs="24" v="DAL" vnn="cowboys" vs="37" p="" rz="" ga="" gt="REG"/><g eid="1983100209" gsis="8224" d="Sun" t="3:00" q="F" k="" h="NYG" hnn="giants" hs="34" v="SD" vnn="chargers" vs="41" p="" rz="" ga="" gt="REG"/><g eid="1983100208" gsis="8224" d="Sun" t="3:00" q="F" k="" h="KC" hnn="chiefs" hs="38" v="STL" vnn="cardinals" vs="14" p="" rz="" ga="" gt="REG"/><g eid="1983100207" gsis="8224" d="Sun" t="3:00" q="F" k="" h="CLE" hnn="browns" hs="9" v="SEA" vnn="seahawks" vs="24" p="" rz="" ga="" gt="REG"/><g eid="1983100206" gsis="8224" d="Sun" t="3:00" q="F" k="" h="GB" hnn="packers" hs="55" v="TB" vnn="buccaneers" vs="14" p="" rz="" ga="" gt="REG"/><g eid="1983100300" gsis="8224" d="Mon" t="3:00" q="F" k="" h="BUF" hnn="bills" hs="10" v="NYJ" vnn="jets" vs="34" p="" rz="" ga="" gt="REG"/></gms></ss>