<?xml version="1.0" encoding="UTF-8"?>
<ss><gms gd="0" w="3" y="1988" t="R"><g eid="1988091808" gsis="8224" d="Sun" t="3:00" q="F" k="" h="SD" hnn="chargers" hs="17" v="SEA" vnn="seahawks" vs="6" p="" rz="" ga="" gt="REG"/><g eid="1988091807" gsis="8224" d="Sun" t="3:00" q="F" k="" h="WAS" hnn="redskins" hs="17" v="PHI" vnn="eagles" vs="10" p="" rz="" ga="" gt="REG"/><g eid="1988091806" gsis="8224" d="Sun" t="3:00" q="F" k="" h="NYJ" hnn="jets" hs="45" v="HOU" vnn="oilers" vs="3" p="" rz="" ga="" gt="REG"/><g eid="1988091805" gsis="8224" d="Sun" t="3:00" q="F" k="" h="TB" hnn="buccaneers" hs="24" v="PHO" vnn="cardinals" vs="30" p="" rz="" ga="" gt="REG"/><g eid="1988091804" gsis="8224" d="Sun" t="3:00" q="F" k="" h="KC" hnn="chiefs" hs="20" v="DEN" vnn="broncos" vs="13" p="" rz="" ga="" gt="REG"/><g eid="1988091803" gsis="8224" d="Sun" t="3:00" q="F" k="" h="PIT" hnn="steelers" hs="12" v="CIN" vnn="bengals" vs="17" p="" rz="" ga="" gt="REG"/><g eid="1988091809" gsis="8224" d="Sun" t="3:00" q="F" k="" h="DAL" hnn="cowboys" hs="10" v="NYG" vnn="giants" vs="12" p="" rz="" ga="" gt="REG"/><g eid="1988091801" gsis="8224" d="Sun" t="3:00" q="F" k="" h="CHI" hnn="bears" hs="7" v="MIN" vnn="vikings" vs="31" p="" rz="" ga="" gt="REG"/><g eid="1988091800" gsis="8224" d="Sun" t="3:00" q="F" k="" h="NE" hnn="patriots" hs="14" v="BUF" vnn="bills" vs="16" p="" rz="" ga="" gt="REG"/><g eid="1988091802" gsis="8224" d="Sun" t="3:00" q="F" k="" h="DET" hnn="lions" hs="14" v="NO" vnn="saints" vs="22" p="" rz="" ga="" gt="REG"/><g eid="1988091812" gsis="8224" d="Sun" t="3:00" q="F" k="" h="RAI" hnn="raiders" hs="17" v="RAM" vnn="rams" vs="22" p="" rz="" ga="" gt="REG"/><g eid="1988091811" gsis="8224" d="Sun" t="3:00" q="F" k="" h="MIA" hnn="dolphins" hs="24" v="GB" vnn="packers" vs="17" p="" rz="" ga="" gt="REG"/><g eid="1988091810" gsis="8224" d="Sun" t="3:00" q="F" k="" h="SF" hnn="49ers" hs="17" v="ATL" vnn="falcons" vs="34" p="" rz="" ga="" gt="REG"/><g eid="1988091900" gsis="8224" d="Mon" t="3:00" q="F" k="" h="CLE" hnn="browns" hs="23" v="IND" vnn="colts" vs="17" p="" rz="" ga="" gt="REG"/></gms></ss>