<?xml version="1.0" encoding="UTF-8"?>
<ss><gms gd="0" w="2" y="1997" t="R"><g eid="1997090713" gsis="1" d="Sun" t="3:00" q="FO" k="" h="ARI" hnn="cardinals" hs="25" v="DAL" vnn="cowboys" vs="22" p="" rz="" ga="" gt="REG"/><g eid="1997090712" gsis="186" d="Sun" t="3:00" q="F" k="" h="PIT" hnn="steelers" hs="14" v="WAS" vnn="redskins" vs="13" p="" rz="" ga="" gt="REG"/><g eid="1997090711" gsis="122" d="Sun" t="3:00" q="FO" k="" h="MIA" hnn="dolphins" hs="16" v="TEN" vnn="oilers" vs="13" p="" rz="" ga="" gt="REG"/><g eid="1997090710" gsis="74" d="Sun" t="3:00" q="F" k="" h="DET" hnn="lions" hs="17" v="TB" vnn="buccaneers" vs="24" p="" rz="" ga="" gt="REG"/><g eid="1997090709" gsis="218" d="Sun" t="3:00" q="F" k="" h="STL" hnn="rams" hs="12" v="SF" vnn="49ers" vs="15" p="" rz="" ga="" gt="REG"/><g eid="1997090708" gsis="145" d="Sun" t="3:00" q="F" k="" h="NO" hnn="saints" hs="6" v="SD" vnn="chargers" vs="20" p="" rz="" ga="" gt="REG"/><g eid="1997090707" gsis="105" d="Sun" t="3:00" q="F" k="" h="JAC" hnn="jaguars" hs="40" v="NYG" vnn="giants" vs="13" p="" rz="" ga="" gt="REG"/><g eid="1997090706" gsis="97" d="Sun" t="3:00" q="F" k="" h="IND" hnn="colts" hs="6" v="NE" vnn="patriots" vs="31" p="" rz="" ga="" gt="REG"/><g eid="1997090705" gsis="41" d="Sun" t="3:00" q="F" k="" h="CHI" hnn="bears" hs="24" v="MIN" vnn="vikings" vs="27" p="" rz="" ga="" gt="REG"/><g eid="1997090704" gsis="177" d="Sun" t="3:00" q="F" k="" h="PHI" hnn="eagles" hs="10" v="GB" vnn="packers" vs="9" p="" rz="" ga="" gt="REG"/><g eid="1997090703" gsis="210" d="Sun" t="3:00" q="F" k="" h="SEA" hnn="seahawks" hs="14" v="DEN" vnn="broncos" vs="35" p="" rz="" ga="" gt="REG"/><g eid="1997090702" gsis="18" d="Sun" t="3:00" q="F" k="" h="BAL" hnn="ravens" hs="23" v="CIN" vnn="bengals" vs="10" p="" rz="" ga="" gt="REG"/><g eid="1997090701" gsis="9" d="Sun" t="3:00" q="F" k="" h="ATL" hnn="falcons" hs="6" v="CAR" vnn="panthers" vs="9" p="" rz="" ga="" gt="REG"/><g eid="1997090700" gsis="161" d="Sun" t="3:00" q="F" k="" h="NYJ" hnn="jets" hs="22" v="BUF" vnn="bills" vs="28" p="" rz="" ga="" gt="REG"/><g eid="1997090800" gsis="169" d="Mon" t="3:00" q="F" k="" h="OAK" hnn="raiders" hs="27" v="KC" vnn="chiefs" vs="28" p="" rz="" ga="" gt="REG"/></gms></ss>