<?xml version="1.0" encoding="UTF-8"?>
<ss><gms gd="0" w="3" y="2004" t="P"><g eid="2004082600" gsis="27200" d="Thu" t="8:00" q="F" k="" h="PHI" hnn="eagles" hs="21" v="PIT" vnn="steelers" vs="27" p="" rz="" ga="" gt="PRE"/><g eid="2004082701" gsis="27202" d="Fri" t="7:00" q="F" k="" h="NYJ" hnn="jets" hs="17" v="NYG" vnn="giants" vs="10" p="" rz="" ga="" gt="PRE"/><g eid="2004082703" gsis="27204" d="Fri" t="8:00" q="F" k="" h="MIN" hnn="vikings" hs="23" v="SF" vnn="49ers" vs="10" p="" rz="" ga="" gt="PRE"/><g eid="2004082702" gsis="27203" d="Fri" t="8:00" q="F" k="" h="JAC" hnn="jaguars" hs="9" v="GB" vnn="packers" vs="7" p="" rz="" ga="" gt="PRE"/><g eid="2004082700" gsis="27201" d="Fri" t="8:00" q="F" k="" h="STL" hnn="rams" hs="28" v="WAS" vnn="redskins" vs="3" p="" rz="" ga="" gt="PRE"/><g eid="2004082704" gsis="27205" d="Fri" t="8:30" q="F" k="" h="CHI" hnn="bears" hs="13" v="NO" vnn="saints" vs="17" p="" rz="" ga="" gt="PRE"/><g eid="2004082705" gsis="27206" d="Fri" t="9:00" q="F" k="" h="DEN" hnn="broncos" hs="31" v="HOU" vnn="texans" vs="17" p="" rz="" ga="" gt="PRE"/><g eid="2004082706" gsis="27207" d="Fri" t="10:00" q="F" k="" h="SD" hnn="chargers" hs="20" v="SEA" vnn="seahawks" vs="26" p="" rz="" ga="" gt="PRE"/><g eid="2004082801" gsis="27209" d="Sat" t="7:00" q="F" k="" h="TB" hnn="buccaneers" hs="17" v="MIA" vnn="dolphins" vs="10" p="" rz="" ga="" gt="PRE"/><g eid="2004082802" gsis="27210" d="Sat" t="7:30" q="F" k="" h="ATL" hnn="falcons" hs="37" v="CIN" vnn="bengals" vs="10" p="" rz="" ga="" gt="PRE"/><g eid="2004082805" gsis="27213" d="Sat" t="8:00" q="F" k="" h="BAL" hnn="ravens" hs="17" v="DET" vnn="lions" vs="6" p="" rz="" ga="" gt="PRE"/><g eid="2004082804" gsis="27212" d="Sat" t="8:00" q="F" k="" h="KC" hnn="chiefs" hs="19" v="CLE" vnn="browns" vs="21" p="" rz="" ga="" gt="PRE"/><g eid="2004082800" gsis="27208" d="Sat" t="8:00" q="F" k="" h="CAR" hnn="panthers" hs="20" v="NE" vnn="patriots" vs="17" p="" rz="" ga="" gt="PRE"/><g eid="2004082803" gsis="27211" d="Sat" t="9:00" q="F" k="" h="IND" hnn="colts" hs="30" v="BUF" vnn="bills" vs="17" p="" rz="" ga="" gt="PRE"/><g eid="2004082806" gsis="27214" d="Sat" t="10:00" q="F" k="" h="ARI" hnn="cardinals" hs="16" v="OAK" vnn="raiders" vs="17" p="" rz="" ga="" gt="PRE"/><g eid="2004083000" gsis="27215" d="Mon" t="8:00" q="F" k="" h="DAL" hnn="cowboys" hs="20" v="TEN" vnn="titans" vs="17" p="" rz="" ga="" gt="PRE"/></gms></ss>